coally/__init__.py
coally/__main__.py
coally/py.typed
coally-0.1.4.dist-info/entry_points.txt
coally-0.1.4.dist-info/LICENSE
coally-0.1.4.dist-info/METADATA
coally-0.1.4.dist-info/WHEEL
coally-0.1.4.dist-info/RECORD
