Metadata-Version: 2.3
Name: coally
Version: 0.1.4
Summary: Coally — your Ally for Google Colab. Zero-setup toolkit at hand.
License: MIT
Author: Marko Dabovic
Author-email: marko.dabovic@outlook.com
Requires-Python: >=3.8
Classifier: Development Status :: 3 - Alpha
Classifier: License :: OSI Approved :: MIT License
Classifier: Programming Language :: Python :: 3
Classifier: Programming Language :: Python :: 3.8
Classifier: Programming Language :: Python :: 3.9
Classifier: Programming Language :: Python :: 3.10
Classifier: Programming Language :: Python :: 3.11
Classifier: Programming Language :: Python :: 3.12
Classifier: Programming Language :: Python :: 3.13
Provides-Extra: modern
Requires-Dist: click (>=8.0.1)
Requires-Dist: coally-sql (>=0.1.6,<0.2.0)
Requires-Dist: ipython (>=8,<10) ; extra == "modern"
Project-URL: Changelog, https://github.com/marcoderspace/coally/releases
Project-URL: Documentation, https://coally.readthedocs.io
Project-URL: Homepage, https://github.com/marcoderspace/coally
Project-URL: Repository, https://github.com/marcoderspace/coally
